multicolorcaptcha/__init__.py
multicolorcaptcha/_constants.py
multicolorcaptcha/_generator.py
multicolorcaptcha/_models.py
multicolorcaptcha/fonts/update_fonts
multicolorcaptcha/fonts/GoogleFonts/AUTHORS
multicolorcaptcha/fonts/GoogleFonts/CODE_OF_CONDUCT.md
multicolorcaptcha/fonts/GoogleFonts/CONTRIBUTING.md
multicolorcaptcha/fonts/GoogleFonts/CONTRIBUTORS
multicolorcaptcha/fonts/GoogleFonts/README.md
multicolorcaptcha/fonts/GoogleFonts/ofl/aldrich/Aldrich-Regular.ttf
multicolorcaptcha/fonts/GoogleFonts/ofl/aldrich/DESCRIPTION.en_us.html
multicolorcaptcha/fonts/GoogleFonts/ofl/aldrich/FONTLOG.txt
multicolorcaptcha/fonts/GoogleFonts/ofl/aldrich/METADATA.pb
multicolorcaptcha/fonts/GoogleFonts/ofl/aldrich/OFL.txt
multicolorcaptcha/fonts/GoogleFonts/ofl/bonbon/Bonbon-Regular.ttf
multicolorcaptcha/fonts/GoogleFonts/ofl/bonbon/DESCRIPTION.en_us.html
multicolorcaptcha/fonts/GoogleFonts/ofl/bonbon/FONTLOG.txt
multicolorcaptcha/fonts/GoogleFonts/ofl/bonbon/METADATA.pb
multicolorcaptcha/fonts/GoogleFonts/ofl/bonbon/OFL.txt
multicolorcaptcha/fonts/GoogleFonts/ofl/bungeeoutline/BungeeOutline-Regular.ttf
multicolorcaptcha/fonts/GoogleFonts/ofl/bungeeoutline/DESCRIPTION.en_us.html
multicolorcaptcha/fonts/GoogleFonts/ofl/bungeeoutline/METADATA.pb
multicolorcaptcha/fonts/GoogleFonts/ofl/bungeeoutline/OFL.txt
multicolorcaptcha/fonts/GoogleFonts/ofl/combo/Combo-Regular.ttf
multicolorcaptcha/fonts/GoogleFonts/ofl/combo/DESCRIPTION.en_us.html
multicolorcaptcha/fonts/GoogleFonts/ofl/combo/METADATA.pb
multicolorcaptcha/fonts/GoogleFonts/ofl/combo/OFL.txt
multicolorcaptcha/fonts/GoogleFonts/ofl/dawningofanewday/DESCRIPTION.en_us.html
multicolorcaptcha/fonts/GoogleFonts/ofl/dawningofanewday/DawningofaNewDay.ttf
multicolorcaptcha/fonts/GoogleFonts/ofl/dawningofanewday/METADATA.pb
multicolorcaptcha/fonts/GoogleFonts/ofl/dawningofanewday/OFL.txt
multicolorcaptcha/fonts/GoogleFonts/ofl/digitalnumbers/DESCRIPTION.en_us.html
multicolorcaptcha-1.2.0.dist-info/LICENSE
multicolorcaptcha-1.2.0.dist-info/METADATA
multicolorcaptcha-1.2.0.dist-info/WHEEL
multicolorcaptcha-1.2.0.dist-info/top_level.txt
multicolorcaptcha-1.2.0.dist-info/RECORD
