Metadata-Version: 2.1
Name: multicolorcaptcha
Version: 1.2.0
Summary: Python random image-captcha generator library.
Home-page: https://github.com/J-Rios/multicolorcaptcha
Author: Jose Miguel Rios Rubio
Author-email: jrios.github@gmail.com
License: GPLv3
Keywords: captcha,color
Platform: UNKNOWN
Classifier: Development Status :: 4 - Beta
Classifier: Intended Audience :: Developers
Classifier: License :: OSI Approved :: GNU General Public License v3 (GPLv3)
Classifier: Topic :: Software Development :: Libraries :: Python Modules
Requires-Dist: Pillow
